setup.py
rate_limit_redis/__init__.py
rate_limit_redis/rate_limit_redis.py
rate_limit_redis/simple_redis.py
rate_limit_redis/version.py
rate_limit_redis.egg-info/PKG-INFO
rate_limit_redis.egg-info/SOURCES.txt
rate_limit_redis.egg-info/dependency_links.txt
rate_limit_redis.egg-info/not-zip-safe
rate_limit_redis.egg-info/requires.txt
rate_limit_redis.egg-info/top_level.txt