Metadata-Version: 1.0
Name: rate-limit-redis
Version: 0.1.1
Summary: A python rate limit tools, which have good compatibility for redis and gevent
Home-page: https://github.com/nmghr9/RateLimitRedis
Author: Henry Hou
Author-email: nmghr9@gmail.com
License: MIT
Platform: UNKNOWN
